{"ticker":"AMZN","source":"GitHub Actions cron \u00b7 Yahoo","updated":"2026-06-16T20:24:09.989835+00:00","spot":246.07000732421875,"previous_close":246.02000427246094,"expiries":[{"date":"2026-06-17","dte":1,"strikes":[{"K":190.0,"call_vol":13,"call_oi":0,"call_last":55.89,"put_vol":39,"put_oi":72,"put_last":0.03},{"K":195.0,"call_vol":23,"call_oi":0,"call_last":50.9,"put_vol":11,"put_oi":114,"put_last":0.05},{"K":200.0,"call_vol":129,"call_oi":81,"call_last":46.27,"put_vol":2,"put_oi":395,"put_last":0.01},{"K":205.0,"call_vol":12,"call_oi":3,"call_last":41.34,"put_vol":4,"put_oi":89,"put_last":0.01},{"K":210.0,"call_vol":2,"call_oi":54,"call_last":37.02,"put_vol":2,"put_oi":52,"put_last":0.01},{"K":215.0,"call_vol":12,"call_oi":178,"call_last":33.3,"put_vol":430,"put_oi":716,"put_last":0.01},{"K":217.5,"call_vol":8,"call_oi":76,"call_last":28.7,"put_vol":21,"put_oi":149,"put_last":0.01},{"K":220.0,"call_vol":14,"call_oi":585,"call_last":26.27,"put_vol":170,"put_oi":1216,"put_last":0.01},{"K":222.5,"call_vol":2,"call_oi":102,"call_last":24.32,"put_vol":22,"put_oi":166,"put_last":0.02},{"K":225.0,"call_vol":939,"call_oi":421,"call_last":21.1,"put_vol":210,"put_oi":371,"put_last":0.05},{"K":227.5,"call_vol":3960,"call_oi":322,"call_last":18.7,"put_vol":282,"put_oi":189,"put_last":0.05},{"K":230.0,"call_vol":404,"call_oi":202,"call_last":15.9,"put_vol":245,"put_oi":587,"put_last":0.06},{"K":232.5,"call_vol":2,"call_oi":94,"call_last":15.95,"put_vol":772,"put_oi":203,"put_last":0.06},{"K":235.0,"call_vol":238,"call_oi":335,"call_last":14.1,"put_vol":500,"put_oi":660,"put_last":0.09},{"K":237.5,"call_vol":380,"call_oi":741,"call_last":8.67,"put_vol":2724,"put_oi":543,"put_last":0.13},{"K":240.0,"call_vol":257,"call_oi":1466,"call_last":6.0,"put_vol":3071,"put_oi":3405,"put_last":0.24},{"K":242.5,"call_vol":499,"call_oi":754,"call_last":4.0,"put_vol":7107,"put_oi":718,"put_last":0.63},{"K":245.0,"call_vol":8165,"call_oi":1445,"call_last":2.24,"put_vol":18954,"put_oi":1198,"put_last":1.45},{"K":247.5,"call_vol":34466,"call_oi":2533,"call_last":1.15,"put_vol":8644,"put_oi":341,"put_last":2.8},{"K":250.0,"call_vol":43738,"call_oi":3574,"call_last":0.49,"put_vol":3054,"put_oi":584,"put_last":4.53},{"K":252.5,"call_vol":16930,"call_oi":6048,"call_last":0.2,"put_vol":123,"put_oi":139,"put_last":6.33},{"K":255.0,"call_vol":9004,"call_oi":6869,"call_last":0.08,"put_vol":149,"put_oi":344,"put_last":9.07},{"K":257.5,"call_vol":2384,"call_oi":1036,"call_last":0.03,"put_vol":2,"put_oi":278,"put_last":11.39},{"K":260.0,"call_vol":2341,"call_oi":1594,"call_last":0.01,"put_vol":169,"put_oi":461,"put_last":14.15},{"K":262.5,"call_vol":1585,"call_oi":529,"call_last":0.01,"put_vol":2,"put_oi":250,"put_last":14.99},{"K":265.0,"call_vol":2372,"call_oi":439,"call_last":0.01,"put_vol":630,"put_oi":0,"put_last":17.61},{"K":267.5,"call_vol":42,"call_oi":199,"call_last":0.01,"put_vol":2926,"put_oi":0,"put_last":21.66},{"K":270.0,"call_vol":73,"call_oi":355,"call_last":0.01,"put_vol":936,"put_oi":1,"put_last":20.75},{"K":272.5,"call_vol":6,"call_oi":44,"call_last":0.01,"put_vol":1184,"put_oi":5,"put_last":25.15},{"K":275.0,"call_vol":5,"call_oi":445,"call_last":0.01,"put_vol":3996,"put_oi":0,"put_last":29.1},{"K":277.5,"call_vol":3,"call_oi":50,"call_last":0.03,"put_vol":4,"put_oi":0,"put_last":28.67},{"K":280.0,"call_vol":60,"call_oi":2479,"call_last":0.01,"put_vol":6,"put_oi":0,"put_last":31.06},{"K":282.5,"call_vol":5,"call_oi":20,"call_last":0.05,"put_vol":18,"put_oi":0,"put_last":36.44},{"K":285.0,"call_vol":2,"call_oi":175,"call_last":0.01,"put_vol":310,"put_oi":0,"put_last":38.93},{"K":287.5,"call_vol":6,"call_oi":7,"call_last":0.06,"put_vol":10,"put_oi":0,"put_last":40.5},{"K":290.0,"call_vol":3,"call_oi":636,"call_last":0.01,"put_vol":16,"put_oi":0,"put_last":41.36},{"K":292.5,"call_vol":1,"call_oi":0,"call_last":0.21,"put_vol":2,"put_oi":6,"put_last":43.68},{"K":295.0,"call_vol":15,"call_oi":21,"call_last":0.13,"put_vol":0,"put_oi":36,"put_last":48.35},{"K":300.0,"call_vol":1,"call_oi":74,"call_last":0.01,"put_vol":0,"put_oi":2,"put_last":54.14},{"K":305.0,"call_vol":1,"call_oi":11,"call_last":0.21,"put_vol":0,"put_oi":0,"put_last":0.0},{"K":310.0,"call_vol":2,"call_oi":1,"call_last":0.01,"put_vol":0,"put_oi":0,"put_last":0.0},{"K":315.0,"call_vol":1,"call_oi":0,"call_last":0.05,"put_vol":0,"put_oi":0,"put_last":0.0},{"K":320.0,"call_vol":2,"call_oi":2,"call_last":0.01,"put_vol":0,"put_oi":0,"put_last":0.0},{"K":325.0,"call_vol":0,"call_oi":1,"call_last":0.21,"put_vol":0,"put_oi":0,"put_last":0.0},{"K":330.0,"call_vol":0,"call_oi":1,"call_last":0.21,"put_vol":0,"put_oi":0,"put_last":0.0},{"K":335.0,"call_vol":1,"call_oi":0,"call_last":0.21,"put_vol":0,"put_oi":0,"put_last":88.71}]},{"date":"2026-06-18","dte":2,"strikes":[{"K":75.0,"call_vol":15,"call_oi":7346,"call_last":171.0,"put_vol":3,"put_oi":1595,"put_last":0.01},{"K":80.0,"call_vol":10,"call_oi":194,"call_last":166.1,"put_vol":1,"put_oi":992,"put_last":0.05},{"K":85.0,"call_vol":5,"call_oi":97,"call_last":162.7,"put_vol":2,"put_oi":352,"put_last":0.01},{"K":90.0,"call_vol":3,"call_oi":31,"call_last":151.0,"put_vol":2,"put_oi":508,"put_last":0.01},{"K":95.0,"call_vol":1,"call_oi":175,"call_last":154.0,"put_vol":4,"put_oi":394,"put_last":0.02},{"K":100.0,"call_vol":36,"call_oi":5144,"call_last":145.66,"put_vol":1,"put_oi":5038,"put_last":0.05},{"K":105.0,"call_vol":13,"call_oi":469,"call_last":140.66,"put_vol":3,"put_oi":2051,"put_last":0.01},{"K":110.0,"call_vol":35,"call_oi":305,"call_last":136.45,"put_vol":1,"put_oi":4124,"put_last":0.04},{"K":115.0,"call_vol":10,"call_oi":276,"call_last":130.95,"put_vol":1,"put_oi":1145,"put_last":0.01},{"K":120.0,"call_vol":4,"call_oi":4451,"call_last":126.4,"put_vol":1,"put_oi":3376,"put_last":0.01},{"K":125.0,"call_vol":7,"call_oi":4769,"call_last":122.01,"put_vol":1,"put_oi":4910,"put_last":0.01},{"K":130.0,"call_vol":1,"call_oi":177,"call_last":116.15,"put_vol":3,"put_oi":5436,"put_last":0.03},{"K":135.0,"call_vol":3,"call_oi":159,"call_last":111.15,"put_vol":2,"put_oi":3564,"put_last":0.01},{"K":140.0,"call_vol":8,"call_oi":3326,"call_last":106.18,"put_vol":1,"put_oi":2584,"put_last":0.15},{"K":145.0,"call_vol":8,"call_oi":475,"call_last":102.43,"put_vol":1,"put_oi":3975,"put_last":0.01},{"K":150.0,"call_vol":28,"call_oi":2449,"call_last":96.28,"put_vol":2,"put_oi":7542,"put_last":0.01},{"K":155.0,"call_vol":1,"call_oi":2640,"call_last":92.36,"put_vol":1,"put_oi":4762,"put_last":0.08},{"K":160.0,"call_vol":41,"call_oi":2194,"call_last":85.7,"put_vol":250,"put_oi":10411,"put_last":0.02},{"K":165.0,"call_vol":7,"call_oi":1942,"call_last":80.91,"put_vol":126,"put_oi":9417,"put_last":0.01},{"K":170.0,"call_vol":8,"call_oi":2681,"call_last":76.55,"put_vol":11,"put_oi":15017,"put_last":0.01},{"K":175.0,"call_vol":9,"call_oi":3934,"call_last":70.7,"put_vol":27,"put_oi":8967,"put_last":0.01},{"K":180.0,"call_vol":11,"call_oi":2427,"call_last":68.7,"put_vol":5,"put_oi":13918,"put_last":0.01},{"K":185.0,"call_vol":12,"call_oi":6889,"call_last":61.0,"put_vol":5,"put_oi":10249,"put_last":0.03},{"K":190.0,"call_vol":114,"call_oi":1441,"call_last":56.34,"put_vol":410,"put_oi":15885,"put_last":0.02},{"K":195.0,"call_vol":12,"call_oi":2729,"call_last":51.0,"put_vol":112,"put_oi":13875,"put_last":0.02},{"K":200.0,"call_vol":89,"call_oi":9103,"call_last":46.47,"put_vol":17,"put_oi":33896,"put_last":0.01},{"K":205.0,"call_vol":38,"call_oi":1909,"call_last":41.22,"put_vol":142,"put_oi":9001,"put_last":0.03},{"K":210.0,"call_vol":328,"call_oi":5323,"call_last":36.0,"put_vol":70,"put_oi":15052,"put_last":0.03},{"K":212.5,"call_vol":0,"call_oi":8,"call_last":24.69,"put_vol":2,"put_oi":321,"put_last":0.03},{"K":215.0,"call_vol":517,"call_oi":5173,"call_last":31.25,"put_vol":3965,"put_oi":20823,"put_last":0.04},{"K":217.5,"call_vol":185,"call_oi":29,"call_last":28.67,"put_vol":18,"put_oi":1587,"put_last":0.06},{"K":220.0,"call_vol":693,"call_oi":25351,"call_last":26.12,"put_vol":469,"put_oi":24643,"put_last":0.05},{"K":222.5,"call_vol":2,"call_oi":51,"call_last":23.85,"put_vol":75,"put_oi":428,"put_last":0.07},{"K":225.0,"call_vol":78,"call_oi":19545,"call_last":20.95,"put_vol":392,"put_oi":10654,"put_last":0.07},{"K":227.5,"call_vol":17,"call_oi":32,"call_last":20.87,"put_vol":122,"put_oi":1783,"put_last":0.09},{"K":230.0,"call_vol":832,"call_oi":22612,"call_last":16.17,"put_vol":655,"put_oi":24164,"put_last":0.11},{"K":232.5,"call_vol":492,"call_oi":715,"call_last":13.72,"put_vol":718,"put_oi":2932,"put_last":0.15},{"K":235.0,"call_vol":1501,"call_oi":11650,"call_last":11.3,"put_vol":1046,"put_oi":13004,"put_last":0.21},{"K":237.5,"call_vol":190,"call_oi":1433,"call_last":9.15,"put_vol":749,"put_oi":3192,"put_last":0.35},{"K":240.0,"call_vol":3189,"call_oi":21020,"call_last":6.93,"put_vol":4317,"put_oi":12028,"put_last":0.69},{"K":242.5,"call_vol":668,"call_oi":5566,"call_last":4.7,"put_vol":2772,"put_oi":3515,"put_last":1.22},{"K":245.0,"call_vol":3601,"call_oi":15746,"call_last":3.16,"put_vol":5502,"put_oi":13378,"put_last":2.19},{"K":247.5,"call_vol":8637,"call_oi":4702,"call_last":1.96,"put_vol":2273,"put_oi":2815,"put_last":3.5},{"K":250.0,"call_vol":30692,"call_oi":31643,"call_last":1.11,"put_vol":1116,"put_oi":12848,"put_last":5.15},{"K":252.5,"call_vol":6412,"call_oi":7478,"call_last":0.62,"put_vol":531,"put_oi":1052,"put_last":7.17},{"K":255.0,"call_vol":7262,"call_oi":19333,"call_last":0.33,"put_vol":591,"put_oi":7673,"put_last":9.46},{"K":257.5,"call_vol":2187,"call_oi":9943,"call_last":0.16,"put_vol":305,"put_oi":764,"put_last":11.35},{"K":260.0,"call_vol":2939,"call_oi":19402,"call_last":0.08,"put_vol":604,"put_oi":9767,"put_last":14.2},{"K":262.5,"call_vol":1869,"call_oi":8828,"call_last":0.04,"put_vol":666,"put_oi":1113,"put_last":15.32},{"K":265.0,"call_vol":847,"call_oi":23157,"call_last":0.02,"put_vol":148,"put_oi":3356,"put_last":19.11},{"K":267.5,"call_vol":269,"call_oi":2012,"call_last":0.02,"put_vol":530,"put_oi":156,"put_last":21.57},{"K":270.0,"call_vol":537,"call_oi":24640,"call_last":0.01,"put_vol":2577,"put_oi":306,"put_last":23.65},{"K":272.5,"call_vol":143,"call_oi":2633,"call_last":0.01,"put_vol":50,"put_oi":1,"put_last":25.65},{"K":275.0,"call_vol":424,"call_oi":18760,"call_last":0.01,"put_vol":1663,"put_oi":469,"put_last":28.7},{"K":277.5,"call_vol":70,"call_oi":13421,"call_last":0.01,"put_vol":515,"put_oi":0,"put_last":29.09},{"K":280.0,"call_vol":190,"call_oi":30015,"call_last":0.01,"put_vol":370,"put_oi":136,"put_last":33.75},{"K":282.5,"call_vol":16,"call_oi":1280,"call_last":0.01,"put_vol":1,"put_oi":3,"put_last":36.47},{"K":285.0,"call_vol":96,"call_oi":13410,"call_last":0.01,"put_vol":410,"put_oi":0,"put_last":37.75},{"K":287.5,"call_vol":65,"call_oi":7142,"call_last":0.01,"put_vol":0,"put_oi":0,"put_last":0.0},{"K":290.0,"call_vol":178,"call_oi":26514,"call_last":0.01,"put_vol":68,"put_oi":9,"put_last":43.3},{"K":292.5,"call_vol":159,"call_oi":937,"call_last":0.01,"put_vol":0,"put_oi":0,"put_last":0.0},{"K":295.0,"call_vol":39,"call_oi":15083,"call_last":0.01,"put_vol":1,"put_oi":0,"put_last":58.75},{"K":300.0,"call_vol":332,"call_oi":44568,"call_last":0.01,"put_vol":30,"put_oi":0,"put_last":52.85},{"K":305.0,"call_vol":11,"call_oi":10542,"call_last":0.02,"put_vol":3,"put_oi":0,"put_last":32.18},{"K":310.0,"call_vol":29,"call_oi":36008,"call_last":0.01,"put_vol":4,"put_oi":0,"put_last":48.55},{"K":315.0,"call_vol":4,"call_oi":15694,"call_last":0.01,"put_vol":5,"put_oi":0,"put_last":45.84},{"K":320.0,"call_vol":258,"call_oi":8970,"call_last":0.01,"put_vol":10,"put_oi":0,"put_last":73.46},{"K":325.0,"call_vol":4,"call_oi":20672,"call_last":0.01,"put_vol":10,"put_oi":0,"put_last":78.4},{"K":330.0,"call_vol":192,"call_oi":4232,"call_last":0.01,"put_vol":1,"put_oi":0,"put_last":65.46},{"K":335.0,"call_vol":1,"call_oi":7578,"call_last":0.02,"put_vol":5,"put_oi":0,"put_last":96.56},{"K":340.0,"call_vol":1,"call_oi":4200,"call_last":0.01,"put_vol":0,"put_oi":5,"put_last":93.4},{"K":345.0,"call_vol":3,"call_oi":1701,"call_last":0.01,"put_vol":19,"put_oi":0,"put_last":81.05},{"K":350.0,"call_vol":2,"call_oi":12370,"call_last":0.01,"put_vol":1,"put_oi":0,"put_last":79.95},{"K":360.0,"call_vol":26,"call_oi":5907,"call_last":0.02,"put_vol":2,"put_oi":0,"put_last":110.97},{"K":370.0,"call_vol":11,"call_oi":8163,"call_last":0.01,"put_vol":1,"put_oi":0,"put_last":121.6},{"K":375.0,"call_vol":2,"call_oi":534,"call_last":0.05,"put_vol":1,"put_oi":0,"put_last":126.6},{"K":380.0,"call_vol":20,"call_oi":1228,"call_last":0.01,"put_vol":0,"put_oi":0,"put_last":116.54}]},{"date":"2026-06-22","dte":6,"strikes":[{"K":175.0,"call_vol":0,"call_oi":0,"call_last":0.0,"put_vol":1,"put_oi":3,"put_last":0.03},{"K":180.0,"call_vol":0,"call_oi":0,"call_last":0.0,"put_vol":0,"put_oi":1,"put_last":0.1},{"K":185.0,"call_vol":1,"call_oi":2,"call_last":61.22,"put_vol":0,"put_oi":1,"put_last":0.11},{"K":190.0,"call_vol":0,"call_oi":2,"call_last":49.75,"put_vol":5,"put_oi":2,"put_last":0.02},{"K":195.0,"call_vol":0,"call_oi":0,"call_last":0.0,"put_vol":4,"put_oi":6,"put_last":0.02},{"K":200.0,"call_vol":1,"call_oi":1,"call_last":48.05,"put_vol":1,"put_oi":17,"put_last":0.05},{"K":205.0,"call_vol":0,"call_oi":0,"call_last":0.0,"put_vol":1,"put_oi":36,"put_last":0.04},{"K":207.5,"call_vol":0,"call_oi":0,"call_last":0.0,"put_vol":51,"put_oi":52,"put_last":0.09},{"K":210.0,"call_vol":0,"call_oi":0,"call_last":0.0,"put_vol":3,"put_oi":336,"put_last":0.07},{"K":212.5,"call_vol":0,"call_oi":0,"call_last":0.0,"put_vol":2,"put_oi":96,"put_last":0.11},{"K":215.0,"call_vol":140,"call_oi":0,"call_last":32.17,"put_vol":522,"put_oi":383,"put_last":0.06},{"K":217.5,"call_vol":0,"call_oi":0,"call_last":0.0,"put_vol":26,"put_oi":97,"put_last":0.08},{"K":220.0,"call_vol":367,"call_oi":5,"call_last":26.42,"put_vol":1,"put_oi":349,"put_last":0.13},{"K":222.5,"call_vol":5,"call_oi":5,"call_last":24.37,"put_vol":8,"put_oi":77,"put_last":0.19},{"K":225.0,"call_vol":495,"call_oi":23,"call_last":21.18,"put_vol":29,"put_oi":63,"put_last":0.21},{"K":227.5,"call_vol":5,"call_oi":2,"call_last":19.8,"put_vol":1,"put_oi":95,"put_last":0.17},{"K":230.0,"call_vol":1701,"call_oi":12,"call_last":17.4,"put_vol":133,"put_oi":793,"put_last":0.21},{"K":232.5,"call_vol":16,"call_oi":7,"call_last":14.95,"put_vol":86,"put_oi":125,"put_last":0.32},{"K":235.0,"call_vol":1198,"call_oi":106,"call_last":11.74,"put_vol":44,"put_oi":1917,"put_last":0.45},{"K":237.5,"call_vol":77,"call_oi":409,"call_last":9.3,"put_vol":419,"put_oi":142,"put_last":0.71},{"K":240.0,"call_vol":643,"call_oi":529,"call_last":7.3,"put_vol":326,"put_oi":495,"put_last":1.14},{"K":242.5,"call_vol":67,"call_oi":456,"call_last":5.6,"put_vol":338,"put_oi":170,"put_last":1.82},{"K":245.0,"call_vol":411,"call_oi":728,"call_last":4.05,"put_vol":1038,"put_oi":336,"put_last":2.87},{"K":247.5,"call_vol":1345,"call_oi":425,"call_last":2.66,"put_vol":166,"put_oi":233,"put_last":3.8},{"K":250.0,"call_vol":2048,"call_oi":1144,"call_last":1.85,"put_vol":71,"put_oi":251,"put_last":5.6},{"K":252.5,"call_vol":983,"call_oi":517,"call_last":1.31,"put_vol":56,"put_oi":16,"put_last":7.52},{"K":255.0,"call_vol":1364,"call_oi":1110,"call_last":0.79,"put_vol":2,"put_oi":19,"put_last":8.53},{"K":257.5,"call_vol":363,"call_oi":284,"call_last":0.49,"put_vol":41,"put_oi":2,"put_last":10.92},{"K":260.0,"call_vol":2189,"call_oi":453,"call_last":0.29,"put_vol":3657,"put_oi":56,"put_last":14.2},{"K":262.5,"call_vol":106,"call_oi":60,"call_last":0.19,"put_vol":2608,"put_oi":5,"put_last":15.45},{"K":265.0,"call_vol":39,"call_oi":75,"call_last":0.1,"put_vol":2271,"put_oi":11,"put_last":19.19},{"K":267.5,"call_vol":15,"call_oi":16,"call_last":0.1,"put_vol":1704,"put_oi":0,"put_last":20.72},{"K":270.0,"call_vol":62,"call_oi":203,"call_last":0.05,"put_vol":4718,"put_oi":0,"put_last":24.2},{"K":272.5,"call_vol":1,"call_oi":15,"call_last":0.06,"put_vol":646,"put_oi":0,"put_last":26.58},{"K":275.0,"call_vol":11,"call_oi":91,"call_last":0.04,"put_vol":1166,"put_oi":0,"put_last":28.95},{"K":280.0,"call_vol":10,"call_oi":34,"call_last":0.02,"put_vol":946,"put_oi":0,"put_last":34.06},{"K":285.0,"call_vol":1,"call_oi":2,"call_last":0.12,"put_vol":0,"put_oi":0,"put_last":0.0},{"K":290.0,"call_vol":102,"call_oi":31,"call_last":0.01,"put_vol":0,"put_oi":0,"put_last":0.0},{"K":295.0,"call_vol":1,"call_oi":1,"call_last":0.09,"put_vol":0,"put_oi":0,"put_last":0.0},{"K":300.0,"call_vol":100,"call_oi":5,"call_last":0.01,"put_vol":0,"put_oi":0,"put_last":0.0},{"K":305.0,"call_vol":2,"call_oi":2,"call_last":0.16,"put_vol":0,"put_oi":0,"put_last":0.0},{"K":310.0,"call_vol":0,"call_oi":1,"call_last":0.07,"put_vol":0,"put_oi":0,"put_last":0.0}]}],"candles":[{"t":1781616600,"o":248.0,"h":248.42999267578125,"l":246.47000122070312,"c":247.9149932861328,"v":2773150},{"t":1781616900,"o":247.91000366210938,"h":247.9250030517578,"l":246.50010681152344,"c":246.7899932861328,"v":619861},{"t":1781617200,"o":246.7899932861328,"h":247.5,"l":246.7899932861328,"c":247.27499389648438,"v":592539},{"t":1781617500,"o":247.25230407714844,"h":247.58999633789062,"l":246.8300018310547,"c":247.04449462890625,"v":488433},{"t":1781617800,"o":247.11000061035156,"h":247.35800170898438,"l":246.4600067138672,"c":246.71499633789062,"v":468451},{"t":1781618100,"o":246.72999572753906,"h":247.52000427246094,"l":246.44200134277344,"c":246.47000122070312,"v":408721},{"t":1781618400,"o":246.4499969482422,"h":246.92999267578125,"l":246.05999755859375,"c":246.33999633789062,"v":420650},{"t":1781618700,"o":246.3300018310547,"h":247.3000030517578,"l":245.4510955810547,"c":247.1999969482422,"v":593046},{"t":1781619000,"o":247.17999267578125,"h":247.29879760742188,"l":246.88999938964844,"c":246.9949951171875,"v":311044},{"t":1781619300,"o":247.0399932861328,"h":247.1199951171875,"l":246.49000549316406,"c":246.94000244140625,"v":307825},{"t":1781619600,"o":246.94000244140625,"h":247.1699981689453,"l":246.77000427246094,"c":246.97999572753906,"v":423030},{"t":1781619900,"o":246.9499969482422,"h":247.0,"l":246.60000610351562,"c":246.80999755859375,"v":313573},{"t":1781620200,"o":246.8300018310547,"h":247.125,"l":246.375,"c":246.43499755859375,"v":364705},{"t":1781620500,"o":246.4600067138672,"h":246.6699981689453,"l":246.22999572753906,"c":246.4499969482422,"v":232216},{"t":1781620800,"o":246.42999267578125,"h":246.9398956298828,"l":246.3300018310547,"c":246.54249572753906,"v":226476},{"t":1781621100,"o":246.5399932861328,"h":247.10000610351562,"l":246.46009826660156,"c":246.91000366210938,"v":288934},{"t":1781621400,"o":246.92999267578125,"h":247.5,"l":246.92999267578125,"c":247.25999450683594,"v":372570},{"t":1781621700,"o":247.28500366210938,"h":248.82000732421875,"l":247.28500366210938,"c":248.38499450683594,"v":567592},{"t":1781622000,"o":248.360107421875,"h":249.39990234375,"l":248.25999450683594,"c":248.48500061035156,"v":554744},{"t":1781622300,"o":248.49000549316406,"h":249.27999877929688,"l":248.11500549316406,"c":249.17999267578125,"v":498429},{"t":1781622600,"o":249.19000244140625,"h":249.47999572753906,"l":249.11000061035156,"c":249.47000122070312,"v":491832},{"t":1781622900,"o":249.4550018310547,"h":249.50999450683594,"l":248.69009399414062,"c":248.69239807128906,"v":317879},{"t":1781623200,"o":248.72999572753906,"h":249.0399932861328,"l":248.5,"c":248.89959716796875,"v":341078},{"t":1781623500,"o":248.8800048828125,"h":249.11000061035156,"l":248.67999267578125,"c":248.7281951904297,"v":278762},{"t":1781623800,"o":248.74000549316406,"h":248.86000061035156,"l":248.28500366210938,"c":248.56500244140625,"v":359830},{"t":1781624100,"o":248.55999755859375,"h":248.6999969482422,"l":248.25,"c":248.61500549316406,"v":288391},{"t":1781624400,"o":248.6300048828125,"h":248.8699951171875,"l":248.2899932861328,"c":248.33999633789062,"v":364875},{"t":1781624700,"o":248.33999633789062,"h":248.47000122070312,"l":247.88070678710938,"c":248.16000366210938,"v":535178},{"t":1781625000,"o":248.19000244140625,"h":248.38999938964844,"l":248.0800018310547,"c":248.1999969482422,"v":287714},{"t":1781625300,"o":248.21499633789062,"h":248.24000549316406,"l":247.92959594726562,"c":248.0,"v":178005},{"t":1781625600,"o":248.0,"h":248.0,"l":247.35499572753906,"c":247.47999572753906,"v":209373},{"t":1781625900,"o":247.47999572753906,"h":247.5800018310547,"l":247.35000610351562,"c":247.45989990234375,"v":220848},{"t":1781626200,"o":247.42999267578125,"h":247.7100067138672,"l":247.2530059814453,"c":247.57110595703125,"v":237460},{"t":1781626500,"o":247.60499572753906,"h":247.6199951171875,"l":247.41009521484375,"c":247.4600067138672,"v":133600},{"t":1781626800,"o":247.4600067138672,"h":247.52000427246094,"l":247.08999633789062,"c":247.2899932861328,"v":210249},{"t":1781627100,"o":247.3000030517578,"h":247.3300018310547,"l":247.11000061035156,"c":247.13999938964844,"v":155716},{"t":1781627400,"o":247.1199951171875,"h":247.31320190429688,"l":247.09500122070312,"c":247.22000122070312,"v":194157},{"t":1781627700,"o":247.22000122070312,"h":247.35000610351562,"l":247.08009338378906,"c":247.27999877929688,"v":227157},{"t":1781628000,"o":247.2899932861328,"h":247.30999755859375,"l":246.60000610351562,"c":246.7899932861328,"v":341801},{"t":1781628300,"o":246.7550048828125,"h":246.88999938964844,"l":246.25,"c":246.27000427246094,"v":315633},{"t":1781628600,"o":246.2899932861328,"h":246.47520446777344,"l":245.9499969482422,"c":246.05999755859375,"v":259679},{"t":1781628900,"o":246.0749969482422,"h":246.2100067138672,"l":245.92999267578125,"c":246.10499572753906,"v":275145},{"t":1781629200,"o":246.11000061035156,"h":246.3000030517578,"l":246.00999450683594,"c":246.14999389648438,"v":223689},{"t":1781629500,"o":246.13499450683594,"h":246.3699951171875,"l":246.11500549316406,"c":246.30999755859375,"v":201921},{"t":1781629800,"o":246.30999755859375,"h":246.36000061035156,"l":246.02000427246094,"c":246.11000061035156,"v":195702},{"t":1781630100,"o":246.10499572753906,"h":246.1490936279297,"l":245.75,"c":245.7799072265625,"v":224523},{"t":1781630400,"o":245.77999877929688,"h":245.9199981689453,"l":245.69000244140625,"c":245.90499877929688,"v":225820},{"t":1781630700,"o":245.9149932861328,"h":245.9600067138672,"l":245.72000122070312,"c":245.8300018310547,"v":204587},{"t":1781631000,"o":245.83999633789062,"h":245.89999389648438,"l":245.65420532226562,"c":245.72000122070312,"v":176450},{"t":1781631300,"o":245.74000549316406,"h":245.82000732421875,"l":245.6300048828125,"c":245.64999389648438,"v":198493},{"t":1781631600,"o":245.66000366210938,"h":245.8159942626953,"l":245.50999450683594,"c":245.625,"v":241387},{"t":1781631900,"o":245.6199951171875,"h":245.86199951171875,"l":245.6199951171875,"c":245.85000610351562,"v":214593},{"t":1781632200,"o":245.85000610351562,"h":246.07000732421875,"l":245.8300018310547,"c":245.9199981689453,"v":199162},{"t":1781632500,"o":245.92999267578125,"h":246.0800018310547,"l":245.67999267578125,"c":245.69749450683594,"v":201562},{"t":1781632800,"o":245.69000244140625,"h":246.19500732421875,"l":245.69000244140625,"c":246.1645965576172,"v":275686},{"t":1781633100,"o":246.13999938964844,"h":246.29620361328125,"l":246.0,"c":246.13099670410156,"v":224775},{"t":1781633400,"o":246.14990234375,"h":246.17999267578125,"l":245.9799041748047,"c":246.17999267578125,"v":143627},{"t":1781633700,"o":246.19000244140625,"h":246.3800048828125,"l":246.02999877929688,"c":246.35000610351562,"v":223968},{"t":1781634000,"o":246.3300018310547,"h":246.47999572753906,"l":246.27999877929688,"c":246.40499877929688,"v":230026},{"t":1781634300,"o":246.3800048828125,"h":246.40499877929688,"l":246.17979431152344,"c":246.2100067138672,"v":361882},{"t":1781634600,"o":246.22000122070312,"h":246.389892578125,"l":246.07000732421875,"c":246.25999450683594,"v":317178},{"t":1781634900,"o":246.25999450683594,"h":246.6300048828125,"l":246.25999450683594,"c":246.61500549316406,"v":256637},{"t":1781635200,"o":246.6199951171875,"h":246.72999572753906,"l":246.36000061035156,"c":246.36500549316406,"v":297116},{"t":1781635500,"o":246.38999938964844,"h":246.52999877929688,"l":246.22000122070312,"c":246.27000427246094,"v":160880},{"t":1781635800,"o":246.25999450683594,"h":246.44000244140625,"l":246.1699981689453,"c":246.36000061035156,"v":236283},{"t":1781636100,"o":246.35499572753906,"h":246.47000122070312,"l":246.33999633789062,"c":246.35499572753906,"v":216404},{"t":1781636400,"o":246.35499572753906,"h":246.38499450683594,"l":245.9499969482422,"c":246.0,"v":205075},{"t":1781636700,"o":245.99000549316406,"h":246.39999389648438,"l":245.91000366210938,"c":246.3529052734375,"v":260395},{"t":1781637000,"o":246.34500122070312,"h":246.44000244140625,"l":246.11000061035156,"c":246.19000244140625,"v":375146},{"t":1781637300,"o":246.2032012939453,"h":246.22500610351562,"l":245.8350067138672,"c":246.2100067138672,"v":334075},{"t":1781637600,"o":246.1999969482422,"h":246.6999969482422,"l":246.14999389648438,"c":246.55999755859375,"v":431029},{"t":1781637900,"o":246.5500030517578,"h":246.60499572753906,"l":246.10000610351562,"c":246.10000610351562,"v":192011},{"t":1781638200,"o":246.1199951171875,"h":246.1999969482422,"l":245.72999572753906,"c":245.7550048828125,"v":269563},{"t":1781638500,"o":245.7899932861328,"h":246.04989624023438,"l":245.77000427246094,"c":246.0,"v":266271},{"t":1781638800,"o":245.9949951171875,"h":246.1199951171875,"l":245.85000610351562,"c":245.99000549316406,"v":319453},{"t":1781639100,"o":245.97999572753906,"h":246.13999938964844,"l":245.66929626464844,"c":245.82000732421875,"v":312025},{"t":1781639400,"o":245.8300018310547,"h":246.10000610351562,"l":245.69000244140625,"c":246.07000732421875,"v":681319},{"t":1781639700,"o":246.0500030517578,"h":246.3300018310547,"l":245.72999572753906,"c":246.07000732421875,"v":1917756}]}