{"ticker":"GOOGL","source":"GitHub Actions cron \u00b7 Yahoo","updated":"2026-06-04T02:04:07.786845+00:00","spot":359.3999938964844,"previous_close":361.8500061035156,"expiries":[{"date":"2026-06-05","dte":1,"strikes":[{"K":100.0,"call_vol":4,"call_oi":1,"call_last":261.45,"put_vol":1,"put_oi":60,"put_last":0.01},{"K":105.0,"call_vol":0,"call_oi":0,"call_last":0.0,"put_vol":1,"put_oi":88,"put_last":0.01},{"K":110.0,"call_vol":60,"call_oi":7,"call_last":251.04,"put_vol":6,"put_oi":83,"put_last":0.63},{"K":115.0,"call_vol":18,"call_oi":3,"call_last":246.07,"put_vol":8,"put_oi":1123,"put_last":0.01},{"K":120.0,"call_vol":18,"call_oi":4,"call_last":241.07,"put_vol":7,"put_oi":1397,"put_last":0.01},{"K":125.0,"call_vol":26,"call_oi":0,"call_last":239.14,"put_vol":4,"put_oi":375,"put_last":0.01},{"K":130.0,"call_vol":2,"call_oi":4,"call_last":231.57,"put_vol":14,"put_oi":1349,"put_last":0.2},{"K":135.0,"call_vol":1,"call_oi":5,"call_last":226.07,"put_vol":1,"put_oi":1101,"put_last":0.01},{"K":140.0,"call_vol":30,"call_oi":4,"call_last":224.88,"put_vol":1,"put_oi":1040,"put_last":0.03},{"K":145.0,"call_vol":42,"call_oi":3,"call_last":219.08,"put_vol":5,"put_oi":10,"put_last":0.15},{"K":150.0,"call_vol":20,"call_oi":1,"call_last":214.09,"put_vol":3,"put_oi":7,"put_last":0.21},{"K":155.0,"call_vol":6,"call_oi":3,"call_last":209.19,"put_vol":1,"put_oi":8,"put_last":0.21},{"K":160.0,"call_vol":102,"call_oi":1,"call_last":201.64,"put_vol":151,"put_oi":151,"put_last":0.01},{"K":165.0,"call_vol":102,"call_oi":1,"call_last":196.64,"put_vol":2,"put_oi":11,"put_last":0.13},{"K":170.0,"call_vol":0,"call_oi":0,"call_last":0.0,"put_vol":4,"put_oi":4,"put_last":0.01},{"K":175.0,"call_vol":1,"call_oi":5,"call_last":222.87,"put_vol":0,"put_oi":0,"put_last":0.0},{"K":180.0,"call_vol":1,"call_oi":8,"call_last":181.2,"put_vol":0,"put_oi":0,"put_last":0.0},{"K":185.0,"call_vol":1,"call_oi":8,"call_last":196.48,"put_vol":2,"put_oi":6,"put_last":0.01},{"K":190.0,"call_vol":0,"call_oi":2,"call_last":207.02,"put_vol":0,"put_oi":0,"put_last":0.0},{"K":195.0,"call_vol":1,"call_oi":22,"call_last":189.95,"put_vol":5,"put_oi":5,"put_last":0.23},{"K":200.0,"call_vol":2,"call_oi":83,"call_last":166.43,"put_vol":0,"put_oi":20,"put_last":0.01},{"K":205.0,"call_vol":1,"call_oi":31,"call_last":155.07,"put_vol":1,"put_oi":4,"put_last":0.12},{"K":210.0,"call_vol":1,"call_oi":0,"call_last":150.17,"put_vol":10,"put_oi":13,"put_last":0.01},{"K":215.0,"call_vol":1,"call_oi":1,"call_last":169.83,"put_vol":2,"put_oi":13,"put_last":0.03},{"K":220.0,"call_vol":1,"call_oi":1,"call_last":165.94,"put_vol":2,"put_oi":2,"put_last":0.04},{"K":225.0,"call_vol":3,"call_oi":5,"call_last":158.17,"put_vol":10,"put_oi":21,"put_last":0.01},{"K":230.0,"call_vol":2,"call_oi":1,"call_last":132.04,"put_vol":6,"put_oi":2,"put_last":0.01},{"K":235.0,"call_vol":1,"call_oi":2,"call_last":129.37,"put_vol":72,"put_oi":60,"put_last":0.19},{"K":240.0,"call_vol":1,"call_oi":1,"call_last":119.29,"put_vol":62,"put_oi":61,"put_last":0.05},{"K":245.0,"call_vol":0,"call_oi":0,"call_last":0.0,"put_vol":1,"put_oi":6,"put_last":0.06},{"K":250.0,"call_vol":10,"call_oi":10,"call_last":134.99,"put_vol":4,"put_oi":49,"put_last":0.24},{"K":255.0,"call_vol":2,"call_oi":3,"call_last":119.5,"put_vol":2,"put_oi":3,"put_last":0.1},{"K":260.0,"call_vol":10,"call_oi":17,"call_last":99.98,"put_vol":6,"put_oi":28,"put_last":0.01},{"K":265.0,"call_vol":0,"call_oi":0,"call_last":0.0,"put_vol":1,"put_oi":42,"put_last":0.99},{"K":270.0,"call_vol":2,"call_oi":2,"call_last":91.81,"put_vol":2,"put_oi":50,"put_last":0.36},{"K":275.0,"call_vol":1,"call_oi":4,"call_last":86.54,"put_vol":1,"put_oi":62,"put_last":0.83},{"K":280.0,"call_vol":1,"call_oi":16,"call_last":97.6,"put_vol":1,"put_oi":73,"put_last":0.1},{"K":285.0,"call_vol":1,"call_oi":7,"call_last":90.87,"put_vol":5,"put_oi":410,"put_last":0.01},{"K":290.0,"call_vol":9,"call_oi":99,"call_last":75.0,"put_vol":121,"put_oi":168,"put_last":0.02},{"K":292.5,"call_vol":0,"call_oi":0,"call_last":0.0,"put_vol":4,"put_oi":3,"put_last":0.02},{"K":295.0,"call_vol":28,"call_oi":64,"call_last":66.11,"put_vol":2,"put_oi":89,"put_last":0.03},{"K":297.5,"call_vol":50,"call_oi":50,"call_last":88.28,"put_vol":1,"put_oi":4,"put_last":0.05},{"K":300.0,"call_vol":14,"call_oi":65,"call_last":60.21,"put_vol":2,"put_oi":589,"put_last":0.01},{"K":302.5,"call_vol":1,"call_oi":2,"call_last":58.3,"put_vol":51,"put_oi":111,"put_last":0.01},{"K":305.0,"call_vol":6,"call_oi":81,"call_last":56.09,"put_vol":1,"put_oi":337,"put_last":0.01},{"K":307.5,"call_vol":0,"call_oi":0,"call_last":0.0,"put_vol":1,"put_oi":3,"put_last":0.05},{"K":310.0,"call_vol":24,"call_oi":54,"call_last":57.0,"put_vol":6,"put_oi":234,"put_last":0.03},{"K":312.5,"call_vol":1,"call_oi":3,"call_last":48.73,"put_vol":2,"put_oi":11,"put_last":0.06},{"K":315.0,"call_vol":3,"call_oi":21,"call_last":49.83,"put_vol":12,"put_oi":219,"put_last":0.02},{"K":317.5,"call_vol":1,"call_oi":13,"call_last":45.62,"put_vol":1,"put_oi":8,"put_last":0.06},{"K":320.0,"call_vol":13,"call_oi":55,"call_last":42.4,"put_vol":64,"put_oi":783,"put_last":0.05},{"K":322.5,"call_vol":3,"call_oi":5,"call_last":39.02,"put_vol":2,"put_oi":26,"put_last":0.07},{"K":325.0,"call_vol":3,"call_oi":78,"call_last":34.95,"put_vol":125,"put_oi":896,"put_last":0.07},{"K":327.5,"call_vol":1,"call_oi":1,"call_last":34.83,"put_vol":1,"put_oi":12,"put_last":0.04},{"K":330.0,"call_vol":10,"call_oi":64,"call_last":31.55,"put_vol":199,"put_oi":874,"put_last":0.09},{"K":332.5,"call_vol":1,"call_oi":8,"call_last":50.53,"put_vol":6,"put_oi":265,"put_last":0.09},{"K":335.0,"call_vol":2,"call_oi":134,"call_last":26.17,"put_vol":242,"put_oi":229,"put_last":0.14},{"K":337.5,"call_vol":1,"call_oi":6,"call_last":24.23,"put_vol":128,"put_oi":164,"put_last":0.16},{"K":340.0,"call_vol":13,"call_oi":1919,"call_last":20.28,"put_vol":871,"put_oi":1312,"put_last":0.2},{"K":342.5,"call_vol":50,"call_oi":3,"call_last":21.9,"put_vol":287,"put_oi":504,"put_last":0.3},{"K":345.0,"call_vol":43,"call_oi":294,"call_last":17.14,"put_vol":2047,"put_oi":1292,"put_last":0.44},{"K":347.5,"call_vol":7,"call_oi":4,"call_last":12.0,"put_vol":1615,"put_oi":555,"put_last":0.68},{"K":350.0,"call_vol":483,"call_oi":403,"call_last":10.4,"put_vol":3282,"put_oi":3308,"put_last":0.95},{"K":352.5,"call_vol":195,"call_oi":209,"call_last":8.07,"put_vol":1193,"put_oi":612,"put_last":1.44},{"K":355.0,"call_vol":178,"call_oi":500,"call_last":6.27,"put_vol":5599,"put_oi":5718,"put_last":2.05},{"K":357.5,"call_vol":1263,"call_oi":295,"call_last":4.93,"put_vol":3675,"put_oi":2703,"put_last":3.2},{"K":360.0,"call_vol":2976,"call_oi":478,"call_last":3.65,"put_vol":18818,"put_oi":12595,"put_last":4.2},{"K":362.5,"call_vol":4806,"call_oi":278,"call_last":2.71,"put_vol":1448,"put_oi":1652,"put_last":5.8},{"K":365.0,"call_vol":8632,"call_oi":997,"call_last":1.85,"put_vol":1276,"put_oi":2299,"put_last":7.55},{"K":367.5,"call_vol":8198,"call_oi":1978,"call_last":1.41,"put_vol":337,"put_oi":1666,"put_last":9.77},{"K":370.0,"call_vol":19696,"call_oi":5555,"call_last":0.99,"put_vol":352,"put_oi":3373,"put_last":11.76},{"K":372.5,"call_vol":2299,"call_oi":4352,"call_last":0.64,"put_vol":268,"put_oi":1143,"put_last":14.42},{"K":375.0,"call_vol":9848,"call_oi":6334,"call_last":0.48,"put_vol":309,"put_oi":1683,"put_last":16.26},{"K":377.5,"call_vol":1153,"call_oi":766,"call_last":0.34,"put_vol":99,"put_oi":766,"put_last":18.78},{"K":380.0,"call_vol":10917,"call_oi":4171,"call_last":0.25,"put_vol":669,"put_oi":2702,"put_last":21.35},{"K":382.5,"call_vol":1294,"call_oi":2645,"call_last":0.18,"put_vol":40,"put_oi":756,"put_last":23.86},{"K":385.0,"call_vol":3278,"call_oi":3627,"call_last":0.12,"put_vol":149,"put_oi":1610,"put_last":25.92},{"K":387.5,"call_vol":996,"call_oi":1529,"call_last":0.12,"put_vol":26,"put_oi":296,"put_last":28.2},{"K":390.0,"call_vol":2249,"call_oi":7318,"call_last":0.08,"put_vol":82,"put_oi":1068,"put_last":31.3},{"K":392.5,"call_vol":353,"call_oi":894,"call_last":0.06,"put_vol":22,"put_oi":160,"put_last":32.93},{"K":395.0,"call_vol":821,"call_oi":2295,"call_last":0.05,"put_vol":17,"put_oi":614,"put_last":34.52},{"K":397.5,"call_vol":301,"call_oi":2155,"call_last":0.06,"put_vol":1,"put_oi":57,"put_last":34.21},{"K":400.0,"call_vol":2144,"call_oi":8815,"call_last":0.04,"put_vol":9,"put_oi":278,"put_last":40.03},{"K":402.5,"call_vol":68,"call_oi":2242,"call_last":0.04,"put_vol":23,"put_oi":36,"put_last":43.43},{"K":405.0,"call_vol":91,"call_oi":2056,"call_last":0.02,"put_vol":23,"put_oi":28,"put_last":39.61},{"K":407.5,"call_vol":1433,"call_oi":1073,"call_last":0.02,"put_vol":25,"put_oi":1,"put_last":17.6},{"K":410.0,"call_vol":108,"call_oi":1804,"call_last":0.02,"put_vol":12,"put_oi":0,"put_last":45.15},{"K":412.5,"call_vol":132,"call_oi":388,"call_last":0.01,"put_vol":0,"put_oi":0,"put_last":0.0},{"K":415.0,"call_vol":196,"call_oi":1147,"call_last":0.02,"put_vol":2,"put_oi":0,"put_last":36.0},{"K":417.5,"call_vol":8,"call_oi":127,"call_last":0.02,"put_vol":0,"put_oi":0,"put_last":0.0},{"K":420.0,"call_vol":37,"call_oi":2448,"call_last":0.01,"put_vol":40,"put_oi":1,"put_last":50.13},{"K":422.5,"call_vol":11,"call_oi":63,"call_last":0.03,"put_vol":0,"put_oi":0,"put_last":0.0},{"K":425.0,"call_vol":37,"call_oi":1847,"call_last":0.01,"put_vol":6,"put_oi":0,"put_last":40.93},{"K":427.5,"call_vol":88,"call_oi":97,"call_last":0.01,"put_vol":0,"put_oi":0,"put_last":0.0},{"K":430.0,"call_vol":49,"call_oi":1174,"call_last":0.03,"put_vol":1,"put_oi":0,"put_last":39.15},{"K":432.5,"call_vol":63,"call_oi":58,"call_last":0.01,"put_vol":0,"put_oi":0,"put_last":0.0},{"K":435.0,"call_vol":24,"call_oi":453,"call_last":0.02,"put_vol":0,"put_oi":0,"put_last":35.92},{"K":437.5,"call_vol":1,"call_oi":706,"call_last":0.01,"put_vol":0,"put_oi":0,"put_last":0.0},{"K":440.0,"call_vol":3,"call_oi":318,"call_last":0.01,"put_vol":4,"put_oi":0,"put_last":40.01},{"K":442.5,"call_vol":1,"call_oi":169,"call_last":0.01,"put_vol":0,"put_oi":0,"put_last":0.0},{"K":445.0,"call_vol":11,"call_oi":329,"call_last":0.02,"put_vol":0,"put_oi":0,"put_last":44.51},{"K":447.5,"call_vol":10,"call_oi":26,"call_last":0.05,"put_vol":0,"put_oi":0,"put_last":0.0},{"K":450.0,"call_vol":205,"call_oi":1230,"call_last":0.02,"put_vol":1,"put_oi":0,"put_last":65.65},{"K":452.5,"call_vol":100,"call_oi":179,"call_last":0.01,"put_vol":0,"put_oi":0,"put_last":0.0},{"K":455.0,"call_vol":40,"call_oi":283,"call_last":0.01,"put_vol":0,"put_oi":0,"put_last":0.0},{"K":457.5,"call_vol":98,"call_oi":99,"call_last":0.01,"put_vol":0,"put_oi":0,"put_last":0.0},{"K":460.0,"call_vol":6,"call_oi":329,"call_last":0.01,"put_vol":0,"put_oi":0,"put_last":0.0},{"K":462.5,"call_vol":5,"call_oi":5,"call_last":0.03,"put_vol":0,"put_oi":0,"put_last":0.0},{"K":465.0,"call_vol":8,"call_oi":268,"call_last":0.26,"put_vol":4,"put_oi":0,"put_last":63.37},{"K":470.0,"call_vol":1,"call_oi":89,"call_last":0.1,"put_vol":0,"put_oi":0,"put_last":0.0},{"K":472.5,"call_vol":1,"call_oi":21,"call_last":0.03,"put_vol":0,"put_oi":0,"put_last":0.0},{"K":475.0,"call_vol":1,"call_oi":184,"call_last":0.01,"put_vol":0,"put_oi":0,"put_last":0.0},{"K":480.0,"call_vol":1,"call_oi":55,"call_last":0.01,"put_vol":0,"put_oi":0,"put_last":0.0},{"K":485.0,"call_vol":1,"call_oi":109,"call_last":0.01,"put_vol":0,"put_oi":0,"put_last":0.0},{"K":490.0,"call_vol":1,"call_oi":10,"call_last":0.08,"put_vol":0,"put_oi":0,"put_last":0.0},{"K":495.0,"call_vol":113,"call_oi":130,"call_last":0.01,"put_vol":0,"put_oi":0,"put_last":0.0},{"K":500.0,"call_vol":1,"call_oi":30,"call_last":0.01,"put_vol":0,"put_oi":0,"put_last":0.0},{"K":505.0,"call_vol":0,"call_oi":13,"call_last":0.02,"put_vol":0,"put_oi":0,"put_last":0.0},{"K":510.0,"call_vol":82,"call_oi":103,"call_last":0.01,"put_vol":0,"put_oi":0,"put_last":0.0},{"K":515.0,"call_vol":5,"call_oi":8,"call_last":0.02,"put_vol":0,"put_oi":0,"put_last":0.0},{"K":520.0,"call_vol":9,"call_oi":34,"call_last":0.02,"put_vol":0,"put_oi":0,"put_last":0.0},{"K":525.0,"call_vol":16,"call_oi":68,"call_last":0.02,"put_vol":0,"put_oi":0,"put_last":0.0},{"K":530.0,"call_vol":3,"call_oi":40,"call_last":0.02,"put_vol":0,"put_oi":0,"put_last":0.0},{"K":535.0,"call_vol":5,"call_oi":147,"call_last":0.02,"put_vol":0,"put_oi":0,"put_last":0.0},{"K":540.0,"call_vol":1,"call_oi":46,"call_last":0.02,"put_vol":0,"put_oi":0,"put_last":0.0},{"K":545.0,"call_vol":2,"call_oi":29,"call_last":0.02,"put_vol":0,"put_oi":0,"put_last":0.0},{"K":550.0,"call_vol":6,"call_oi":25,"call_last":0.01,"put_vol":0,"put_oi":0,"put_last":0.0}]},{"date":"2026-06-08","dte":4,"strikes":[{"K":325.0,"call_vol":0,"call_oi":0,"call_last":0.0,"put_vol":22,"put_oi":48,"put_last":0.08},{"K":330.0,"call_vol":0,"call_oi":0,"call_last":0.0,"put_vol":52,"put_oi":31,"put_last":0.19},{"K":335.0,"call_vol":0,"call_oi":0,"call_last":0.0,"put_vol":44,"put_oi":81,"put_last":0.37},{"K":340.0,"call_vol":0,"call_oi":0,"call_last":0.0,"put_vol":48,"put_oi":146,"put_last":0.6},{"K":342.5,"call_vol":0,"call_oi":0,"call_last":0.0,"put_vol":33,"put_oi":56,"put_last":0.77},{"K":345.0,"call_vol":2,"call_oi":1,"call_last":21.7,"put_vol":164,"put_oi":320,"put_last":1.05},{"K":347.5,"call_vol":0,"call_oi":0,"call_last":0.0,"put_vol":131,"put_oi":147,"put_last":1.21},{"K":350.0,"call_vol":16,"call_oi":23,"call_last":11.91,"put_vol":104,"put_oi":331,"put_last":2.0},{"K":352.5,"call_vol":0,"call_oi":0,"call_last":0.0,"put_vol":67,"put_oi":87,"put_last":2.16},{"K":355.0,"call_vol":36,"call_oi":21,"call_last":7.4,"put_vol":243,"put_oi":325,"put_last":3.49},{"K":357.5,"call_vol":0,"call_oi":0,"call_last":0.0,"put_vol":120,"put_oi":161,"put_last":4.47},{"K":360.0,"call_vol":226,"call_oi":126,"call_last":4.75,"put_vol":205,"put_oi":221,"put_last":5.89},{"K":362.5,"call_vol":0,"call_oi":0,"call_last":0.0,"put_vol":118,"put_oi":173,"put_last":7.75},{"K":365.0,"call_vol":671,"call_oi":142,"call_last":3.05,"put_vol":55,"put_oi":184,"put_last":8.35},{"K":367.5,"call_vol":150,"call_oi":172,"call_last":2.07,"put_vol":26,"put_oi":284,"put_last":10.93},{"K":370.0,"call_vol":847,"call_oi":221,"call_last":1.78,"put_vol":174,"put_oi":318,"put_last":12.11},{"K":372.5,"call_vol":231,"call_oi":1144,"call_last":1.38,"put_vol":4,"put_oi":47,"put_last":14.48},{"K":375.0,"call_vol":561,"call_oi":257,"call_last":0.95,"put_vol":52,"put_oi":340,"put_last":16.8},{"K":377.5,"call_vol":113,"call_oi":184,"call_last":0.73,"put_vol":59,"put_oi":83,"put_last":19.36},{"K":380.0,"call_vol":402,"call_oi":331,"call_last":0.6,"put_vol":11,"put_oi":141,"put_last":21.64},{"K":382.5,"call_vol":93,"call_oi":260,"call_last":0.55,"put_vol":4,"put_oi":43,"put_last":23.01},{"K":385.0,"call_vol":382,"call_oi":477,"call_last":0.38,"put_vol":8,"put_oi":143,"put_last":26.02},{"K":387.5,"call_vol":53,"call_oi":251,"call_last":0.35,"put_vol":25,"put_oi":30,"put_last":14.4},{"K":390.0,"call_vol":179,"call_oi":358,"call_last":0.25,"put_vol":2,"put_oi":7,"put_last":30.65},{"K":392.5,"call_vol":417,"call_oi":290,"call_last":0.28,"put_vol":3,"put_oi":3,"put_last":24.77},{"K":395.0,"call_vol":39,"call_oi":143,"call_last":0.22,"put_vol":14,"put_oi":18,"put_last":29.88},{"K":397.5,"call_vol":3,"call_oi":137,"call_last":0.18,"put_vol":19,"put_oi":17,"put_last":30.76},{"K":400.0,"call_vol":81,"call_oi":1042,"call_last":0.15,"put_vol":0,"put_oi":0,"put_last":0.0},{"K":402.5,"call_vol":21,"call_oi":98,"call_last":0.15,"put_vol":3,"put_oi":24,"put_last":22.73},{"K":405.0,"call_vol":2,"call_oi":123,"call_last":0.13,"put_vol":0,"put_oi":12,"put_last":16.91},{"K":407.5,"call_vol":2,"call_oi":25,"call_last":0.26,"put_vol":0,"put_oi":0,"put_last":0.0},{"K":410.0,"call_vol":14,"call_oi":271,"call_last":0.1,"put_vol":2,"put_oi":1,"put_last":29.71},{"K":412.5,"call_vol":4,"call_oi":48,"call_last":0.07,"put_vol":0,"put_oi":0,"put_last":0.0},{"K":415.0,"call_vol":11,"call_oi":65,"call_last":0.12,"put_vol":0,"put_oi":0,"put_last":0.0},{"K":417.5,"call_vol":23,"call_oi":54,"call_last":0.15,"put_vol":0,"put_oi":0,"put_last":0.0},{"K":420.0,"call_vol":4,"call_oi":18,"call_last":0.08,"put_vol":0,"put_oi":0,"put_last":0.0},{"K":425.0,"call_vol":4,"call_oi":205,"call_last":0.1,"put_vol":2,"put_oi":0,"put_last":62.92},{"K":427.5,"call_vol":3,"call_oi":3,"call_last":0.43,"put_vol":0,"put_oi":0,"put_last":0.0},{"K":430.0,"call_vol":6,"call_oi":105,"call_last":0.09,"put_vol":0,"put_oi":0,"put_last":0.0},{"K":435.0,"call_vol":63,"call_oi":63,"call_last":0.36,"put_vol":0,"put_oi":0,"put_last":0.0},{"K":440.0,"call_vol":0,"call_oi":202,"call_last":0.29,"put_vol":0,"put_oi":0,"put_last":0.0},{"K":445.0,"call_vol":22,"call_oi":40,"call_last":0.12,"put_vol":0,"put_oi":0,"put_last":0.0},{"K":450.0,"call_vol":98,"call_oi":12,"call_last":0.03,"put_vol":0,"put_oi":0,"put_last":0.0},{"K":455.0,"call_vol":1,"call_oi":8,"call_last":0.12,"put_vol":0,"put_oi":0,"put_last":0.0},{"K":460.0,"call_vol":7,"call_oi":9,"call_last":0.01,"put_vol":0,"put_oi":0,"put_last":0.0},{"K":465.0,"call_vol":0,"call_oi":1,"call_last":0.16,"put_vol":0,"put_oi":0,"put_last":0.0},{"K":470.0,"call_vol":2,"call_oi":3,"call_last":0.01,"put_vol":0,"put_oi":0,"put_last":0.0}]},{"date":"2026-06-10","dte":6,"strikes":[{"K":325.0,"call_vol":0,"call_oi":5,"call_last":65.56,"put_vol":15,"put_oi":44,"put_last":0.27},{"K":330.0,"call_vol":0,"call_oi":0,"call_last":0.0,"put_vol":31,"put_oi":44,"put_last":0.4},{"K":332.5,"call_vol":0,"call_oi":0,"call_last":0.0,"put_vol":25,"put_oi":19,"put_last":0.57},{"K":335.0,"call_vol":0,"call_oi":0,"call_last":0.0,"put_vol":159,"put_oi":212,"put_last":0.62},{"K":337.5,"call_vol":0,"call_oi":0,"call_last":0.0,"put_vol":8,"put_oi":7,"put_last":0.87},{"K":340.0,"call_vol":0,"call_oi":0,"call_last":0.0,"put_vol":272,"put_oi":57,"put_last":1.2},{"K":342.5,"call_vol":0,"call_oi":0,"call_last":0.0,"put_vol":28,"put_oi":22,"put_last":1.48},{"K":345.0,"call_vol":0,"call_oi":0,"call_last":0.0,"put_vol":31,"put_oi":31,"put_last":2.0},{"K":347.5,"call_vol":0,"call_oi":0,"call_last":0.0,"put_vol":49,"put_oi":12,"put_last":2.39},{"K":350.0,"call_vol":0,"call_oi":0,"call_last":0.0,"put_vol":70,"put_oi":82,"put_last":3.0},{"K":352.5,"call_vol":0,"call_oi":0,"call_last":0.0,"put_vol":29,"put_oi":51,"put_last":3.4},{"K":355.0,"call_vol":0,"call_oi":0,"call_last":0.0,"put_vol":107,"put_oi":130,"put_last":4.5},{"K":357.5,"call_vol":0,"call_oi":0,"call_last":0.0,"put_vol":50,"put_oi":19,"put_last":4.76},{"K":360.0,"call_vol":85,"call_oi":48,"call_last":5.87,"put_vol":73,"put_oi":217,"put_last":5.85},{"K":362.5,"call_vol":86,"call_oi":18,"call_last":5.0,"put_vol":131,"put_oi":66,"put_last":8.46},{"K":365.0,"call_vol":124,"call_oi":42,"call_last":4.03,"put_vol":42,"put_oi":192,"put_last":9.49},{"K":367.5,"call_vol":167,"call_oi":32,"call_last":3.4,"put_vol":97,"put_oi":84,"put_last":10.95},{"K":370.0,"call_vol":0,"call_oi":0,"call_last":0.0,"put_vol":28,"put_oi":114,"put_last":13.78},{"K":372.5,"call_vol":151,"call_oi":40,"call_last":2.25,"put_vol":27,"put_oi":25,"put_last":14.95},{"K":375.0,"call_vol":106,"call_oi":158,"call_last":1.63,"put_vol":11,"put_oi":117,"put_last":17.05},{"K":377.5,"call_vol":38,"call_oi":52,"call_last":1.9,"put_vol":3,"put_oi":35,"put_last":18.07},{"K":380.0,"call_vol":151,"call_oi":1643,"call_last":1.21,"put_vol":1,"put_oi":45,"put_last":22.27},{"K":382.5,"call_vol":61,"call_oi":154,"call_last":1.15,"put_vol":6,"put_oi":14,"put_last":22.05},{"K":385.0,"call_vol":59,"call_oi":167,"call_last":0.78,"put_vol":0,"put_oi":0,"put_last":0.0},{"K":387.5,"call_vol":2,"call_oi":63,"call_last":0.85,"put_vol":1,"put_oi":1,"put_last":10.71},{"K":390.0,"call_vol":104,"call_oi":188,"call_last":0.68,"put_vol":4,"put_oi":6,"put_last":29.03},{"K":392.5,"call_vol":23,"call_oi":123,"call_last":0.5,"put_vol":0,"put_oi":0,"put_last":0.0},{"K":395.0,"call_vol":13,"call_oi":109,"call_last":0.46,"put_vol":1,"put_oi":1,"put_last":15.89},{"K":397.5,"call_vol":53,"call_oi":100,"call_last":0.58,"put_vol":0,"put_oi":0,"put_last":0.0},{"K":400.0,"call_vol":483,"call_oi":1290,"call_last":0.28,"put_vol":0,"put_oi":0,"put_last":0.0},{"K":402.5,"call_vol":5,"call_oi":53,"call_last":0.3,"put_vol":0,"put_oi":16,"put_last":16.2},{"K":405.0,"call_vol":10,"call_oi":27,"call_last":0.32,"put_vol":0,"put_oi":11,"put_last":17.83},{"K":407.5,"call_vol":1,"call_oi":11,"call_last":0.32,"put_vol":0,"put_oi":0,"put_last":0.0},{"K":410.0,"call_vol":4,"call_oi":398,"call_last":0.21,"put_vol":0,"put_oi":0,"put_last":0.0},{"K":412.5,"call_vol":4,"call_oi":12,"call_last":0.4,"put_vol":0,"put_oi":0,"put_last":0.0},{"K":415.0,"call_vol":1,"call_oi":112,"call_last":0.2,"put_vol":0,"put_oi":0,"put_last":0.0},{"K":417.5,"call_vol":5,"call_oi":5,"call_last":0.88,"put_vol":0,"put_oi":0,"put_last":0.0},{"K":420.0,"call_vol":1,"call_oi":11,"call_last":0.27,"put_vol":0,"put_oi":0,"put_last":0.0},{"K":422.5,"call_vol":0,"call_oi":1,"call_last":1.06,"put_vol":0,"put_oi":0,"put_last":0.0},{"K":425.0,"call_vol":2,"call_oi":27,"call_last":0.09,"put_vol":0,"put_oi":0,"put_last":0.0},{"K":430.0,"call_vol":1,"call_oi":5,"call_last":0.2,"put_vol":0,"put_oi":0,"put_last":0.0},{"K":435.0,"call_vol":1,"call_oi":1,"call_last":0.19,"put_vol":0,"put_oi":0,"put_last":0.0},{"K":445.0,"call_vol":2,"call_oi":19,"call_last":0.18,"put_vol":0,"put_oi":0,"put_last":0.0},{"K":455.0,"call_vol":2,"call_oi":3,"call_last":0.19,"put_vol":0,"put_oi":0,"put_last":0.0},{"K":460.0,"call_vol":7,"call_oi":16,"call_last":0.08,"put_vol":0,"put_oi":0,"put_last":0.0},{"K":465.0,"call_vol":2,"call_oi":10,"call_last":0.13,"put_vol":0,"put_oi":0,"put_last":0.0},{"K":470.0,"call_vol":7,"call_oi":5,"call_last":0.01,"put_vol":0,"put_oi":0,"put_last":0.0}]}],"candles":[{"t":1780493400,"o":362.0299987792969,"h":366.45001220703125,"l":361.0,"c":364.0899963378906,"v":7157219},{"t":1780493700,"o":364.1000061035156,"h":364.1499938964844,"l":361.3999938964844,"c":363.0799865722656,"v":1629008},{"t":1780494000,"o":363.0450134277344,"h":364.8999938964844,"l":361.94000244140625,"c":363.6499938964844,"v":1326597},{"t":1780494300,"o":363.6600036621094,"h":364.4599914550781,"l":360.9100036621094,"c":362.78009033203125,"v":1313746},{"t":1780494600,"o":362.7799987792969,"h":363.0,"l":361.5799865722656,"c":362.2300109863281,"v":815495},{"t":1780494900,"o":362.2900085449219,"h":364.25,"l":361.9800109863281,"c":364.18499755859375,"v":944578},{"t":1780495200,"o":364.18499755859375,"h":365.94500732421875,"l":364.1199951171875,"c":365.5299987792969,"v":1051976},{"t":1780495500,"o":365.54998779296875,"h":366.1400146484375,"l":363.8900146484375,"c":364.3800048828125,"v":711277},{"t":1780495800,"o":364.3999938964844,"h":365.1400146484375,"l":363.5,"c":364.2749938964844,"v":555680},{"t":1780496100,"o":364.260009765625,"h":364.260009765625,"l":361.1000061035156,"c":361.57501220703125,"v":536136},{"t":1780496400,"o":361.57501220703125,"h":362.79998779296875,"l":361.32000732421875,"c":361.9599914550781,"v":664891},{"t":1780496700,"o":361.9800109863281,"h":362.3699951171875,"l":361.0,"c":361.4783020019531,"v":497294},{"t":1780497000,"o":361.4700012207031,"h":362.6499938964844,"l":361.3999938964844,"c":362.5,"v":633017},{"t":1780497300,"o":362.5199890136719,"h":363.6700134277344,"l":362.4200134277344,"c":363.6600036621094,"v":363306},{"t":1780497600,"o":363.635009765625,"h":363.9399108886719,"l":362.57000732421875,"c":362.6400146484375,"v":339657},{"t":1780497900,"o":362.5199890136719,"h":362.79998779296875,"l":361.44000244140625,"c":362.05999755859375,"v":571440},{"t":1780498200,"o":362.05999755859375,"h":362.3949890136719,"l":361.81500244140625,"c":361.9100036621094,"v":326523},{"t":1780498500,"o":361.8800048828125,"h":362.0249938964844,"l":360.6400146484375,"c":361.25,"v":430115},{"t":1780498800,"o":361.2699890136719,"h":361.489990234375,"l":360.0400085449219,"c":360.2449951171875,"v":399798},{"t":1780499100,"o":360.2300109863281,"h":360.760009765625,"l":360.0504150390625,"c":360.5,"v":309122},{"t":1780499400,"o":360.5299987792969,"h":360.80999755859375,"l":359.385009765625,"c":359.6958923339844,"v":1008186},{"t":1780499700,"o":359.6700134277344,"h":359.70001220703125,"l":358.7900085449219,"c":359.239990234375,"v":789426},{"t":1780500000,"o":359.2099914550781,"h":359.2699890136719,"l":358.5299987792969,"c":358.989990234375,"v":513642},{"t":1780500300,"o":358.9800109863281,"h":359.75,"l":358.7699890136719,"c":359.6400146484375,"v":375462},{"t":1780500600,"o":359.6199951171875,"h":359.6400146484375,"l":359.0400085449219,"c":359.1400146484375,"v":324244},{"t":1780500900,"o":359.1000061035156,"h":359.3299865722656,"l":358.8599853515625,"c":359.1099853515625,"v":338169},{"t":1780501200,"o":359.0899963378906,"h":360.0199890136719,"l":358.9849853515625,"c":360.0101013183594,"v":282481},{"t":1780501500,"o":360.010009765625,"h":360.3299865722656,"l":359.239990234375,"c":360.1499938964844,"v":417892},{"t":1780501800,"o":360.1300048828125,"h":360.31988525390625,"l":358.80999755859375,"c":359.3299865722656,"v":185819},{"t":1780502100,"o":359.30010986328125,"h":359.7300109863281,"l":359.17999267578125,"c":359.6400146484375,"v":347670},{"t":1780502400,"o":359.6600036621094,"h":360.7799987792969,"l":359.54998779296875,"c":360.760009765625,"v":358722},{"t":1780502700,"o":360.7799987792969,"h":361.1700134277344,"l":359.94000244140625,"c":359.9678039550781,"v":486000},{"t":1780503000,"o":359.9549865722656,"h":360.17999267578125,"l":359.4100036621094,"c":359.4549865722656,"v":330485},{"t":1780503300,"o":359.4549865722656,"h":359.625,"l":358.9302062988281,"c":359.05499267578125,"v":200626},{"t":1780503600,"o":359.0799865722656,"h":359.1000061035156,"l":358.6000061035156,"c":358.6499938964844,"v":164538},{"t":1780503900,"o":358.6499938964844,"h":359.2099914550781,"l":358.45001220703125,"c":359.1099853515625,"v":348292},{"t":1780504200,"o":359.0849914550781,"h":359.70001220703125,"l":359.07000732421875,"c":359.68499755859375,"v":289931},{"t":1780504500,"o":359.67010498046875,"h":360.44000244140625,"l":359.4200134277344,"c":359.6199951171875,"v":473073},{"t":1780504800,"o":359.6000061035156,"h":359.7900085449219,"l":359.05499267578125,"c":359.6099853515625,"v":342359},{"t":1780505100,"o":360.4800109863281,"h":361.385009765625,"l":360.4700012207031,"c":361.010009765625,"v":368321},{"t":1780505400,"o":360.9801025390625,"h":361.5950012207031,"l":360.5401916503906,"c":360.55499267578125,"v":298416},{"t":1780505700,"o":360.6000061035156,"h":361.45001220703125,"l":360.5199890136719,"c":361.3399963378906,"v":168414},{"t":1780506000,"o":361.3599853515625,"h":361.3599853515625,"l":360.4949951171875,"c":360.7900085449219,"v":194295},{"t":1780506300,"o":360.82000732421875,"h":361.3399963378906,"l":360.6300048828125,"c":361.3399963378906,"v":222039},{"t":1780506600,"o":361.32000732421875,"h":361.45989990234375,"l":360.55999755859375,"c":361.0299987792969,"v":185130},{"t":1780506900,"o":361.010009765625,"h":361.8299865722656,"l":360.95001220703125,"c":361.7950134277344,"v":196946},{"t":1780507200,"o":361.7699890136719,"h":362.44000244140625,"l":361.57000732421875,"c":362.2699890136719,"v":440024},{"t":1780507500,"o":362.04998779296875,"h":362.30999755859375,"l":361.05499267578125,"c":361.5899963378906,"v":236649},{"t":1780507800,"o":361.6099853515625,"h":361.75,"l":361.1300048828125,"c":361.3699951171875,"v":231458},{"t":1780508100,"o":361.289794921875,"h":361.389892578125,"l":360.79998779296875,"c":361.17498779296875,"v":172323},{"t":1780508400,"o":361.1700134277344,"h":362.1260070800781,"l":361.1300048828125,"c":361.6099853515625,"v":222235},{"t":1780508700,"o":361.6199951171875,"h":361.7300109863281,"l":360.3500061035156,"c":360.6202087402344,"v":237951},{"t":1780509000,"o":360.614990234375,"h":360.80999755859375,"l":360.0899963378906,"c":360.2900085449219,"v":225880},{"t":1780509300,"o":360.30999755859375,"h":360.55999755859375,"l":360.2200012207031,"c":360.55999755859375,"v":185115},{"t":1780509600,"o":360.5400085449219,"h":360.70001220703125,"l":360.2200012207031,"c":360.4399108886719,"v":275854},{"t":1780509900,"o":360.4150085449219,"h":360.44000244140625,"l":359.6400146484375,"c":359.7900085449219,"v":526278},{"t":1780510200,"o":359.79998779296875,"h":359.8900146484375,"l":359.17999267578125,"c":359.2799987792969,"v":319738},{"t":1780510500,"o":359.2799987792969,"h":359.760009765625,"l":359.2799987792969,"c":359.5299987792969,"v":328943},{"t":1780510800,"o":359.5299987792969,"h":359.69000244140625,"l":359.1700134277344,"c":359.3699951171875,"v":291146},{"t":1780511100,"o":359.3699951171875,"h":359.9150085449219,"l":359.2799987792969,"c":359.5899963378906,"v":287986},{"t":1780511400,"o":359.5899963378906,"h":359.94000244140625,"l":359.5400085449219,"c":359.6099853515625,"v":244016},{"t":1780511700,"o":359.5899963378906,"h":360.3299865722656,"l":359.5899963378906,"c":359.9800109863281,"v":245742},{"t":1780512000,"o":360.0299987792969,"h":360.6400146484375,"l":359.6700134277344,"c":360.5199890136719,"v":335853},{"t":1780512300,"o":360.5299987792969,"h":361.260009765625,"l":360.42999267578125,"c":360.6600036621094,"v":314957},{"t":1780512600,"o":360.6400146484375,"h":361.3599853515625,"l":360.3900146484375,"c":361.0849914550781,"v":264944},{"t":1780512900,"o":361.07000732421875,"h":361.42999267578125,"l":360.4100036621094,"c":360.57501220703125,"v":299850},{"t":1780513200,"o":360.55999755859375,"h":360.6600036621094,"l":359.6300048828125,"c":359.7699890136719,"v":297492},{"t":1780513500,"o":359.75,"h":360.0450134277344,"l":359.30999755859375,"c":360.0249938964844,"v":376076},{"t":1780513800,"o":360.0400085449219,"h":360.5849914550781,"l":359.5799865722656,"c":360.3601989746094,"v":404580},{"t":1780514100,"o":360.3699951171875,"h":360.44000244140625,"l":359.5899963378906,"c":359.67999267578125,"v":409174},{"t":1780514400,"o":359.6700134277344,"h":359.9200134277344,"l":359.44000244140625,"c":359.6600036621094,"v":389796},{"t":1780514700,"o":359.6600036621094,"h":360.32000732421875,"l":359.56500244140625,"c":360.0450134277344,"v":349662},{"t":1780515000,"o":360.0400085449219,"h":360.07000732421875,"l":359.6300048828125,"c":359.760009765625,"v":301559},{"t":1780515300,"o":359.760009765625,"h":359.7900085449219,"l":359.4299011230469,"c":359.510009765625,"v":660672},{"t":1780515600,"o":359.5,"h":359.5799865722656,"l":358.8299865722656,"c":359.0150146484375,"v":519790},{"t":1780515900,"o":359.010009765625,"h":359.3699951171875,"l":358.7749938964844,"c":359.0,"v":502938},{"t":1780516200,"o":359.0199890136719,"h":359.04998779296875,"l":358.29998779296875,"c":358.42999267578125,"v":1042686},{"t":1780516500,"o":358.3999938964844,"h":359.45001220703125,"l":358.0799865722656,"c":359.3999938964844,"v":2440314}]}